pvault/__init__.py
pvault/auth.py
pvault/config.py
pvault/crypto.py
pvault/db.py
pvault/generator.py
pvault/handler.py
pvault/pv.py
pvault-1.1.3a0.data/scripts/pv.py
pvault-1.1.3a0.dist-info/LICENSE
pvault-1.1.3a0.dist-info/METADATA
pvault-1.1.3a0.dist-info/WHEEL
pvault-1.1.3a0.dist-info/entry_points.txt
pvault-1.1.3a0.dist-info/top_level.txt
pvault-1.1.3a0.dist-info/RECORD
