Metadata-Version: 2.1
Name: pvault
Version: 1.1.3a0
Summary: A password manager package
Home-page: https://github.com/oluwafenyi/password-vault
Author: oluwafenyi
Author-email: o.enyioma@gmail.com
License: MIT
Download-URL: https://pypi.org/project/pvault/
Keywords: password crypto management
Platform: UNKNOWN
Classifier: Development Status :: 3 - Alpha
Classifier: Programming Language :: Python :: 3
Classifier: License :: OSI Approved :: MIT License
Classifier: Operating System :: Microsoft :: Windows
Classifier: Operating System :: POSIX :: Linux
Requires-Python: >=3.5
Requires-Dist: cryptography (==2.7)
Requires-Dist: pyAesCrypt (==0.4.3)
Requires-Dist: pyperclip (==1.7.0)
